awstk/__init__.py
awstk/__main__.py
awstk/closest_match.py
awstk/cloudformation.py
awstk/cloudwatch.py
awstk/dashboard.py
awstk/db.py
awstk/secretsmanager.py
awstk-0.3.1.dist-info/METADATA
awstk-0.3.1.dist-info/LICENSE
awstk-0.3.1.dist-info/WHEEL
awstk-0.3.1.dist-info/entry_points.txt
awstk-0.3.1.dist-info/RECORD
