Metadata-Version: 2.1
Name: awstk
Version: 0.3.1
Summary: useful aws helper functions for cli administration of AWS
Home-page: https://github.com/cnboonhan/awstk
License: Apache Software License 2.0
Author: awstk
Author-email: charayaphan.nakorn.boon.han@gmail.com
Requires-Python: >=3.7,<4.0
Classifier: Development Status :: 3 - Alpha
Classifier: Intended Audience :: Developers
Classifier: License :: OSI Approved :: Apache Software License
Classifier: License :: Other/Proprietary License
Classifier: Operating System :: OS Independent
Classifier: Programming Language :: Python :: 3
Classifier: Programming Language :: Python :: 3.7
Classifier: Programming Language :: Python :: 3.8
Classifier: Programming Language :: Python :: 3.9
Classifier: Programming Language :: Python :: 3.10
Classifier: Programming Language :: Python :: 3.11
Classifier: Programming Language :: Python :: 3
Classifier: Programming Language :: Python :: 3.7
Classifier: Programming Language :: Python :: 3.8
Classifier: Programming Language :: Python :: 3.9
Classifier: Topic :: Software Development :: Libraries :: Python Modules
Requires-Dist: boto3 (>=1.26.37,<2.0.0)
Requires-Dist: importlib_metadata (>=4.5.0,<5.0.0) ; python_version < "3.8"
Requires-Dist: rich (>=10.14.0,<11.0.0)
Requires-Dist: sqlitedict (>=2.1.0,<3.0.0)
Requires-Dist: typer[all] (>=0.4.0,<0.5.0)
Project-URL: Repository, https://github.com/cnboonhan/awstk
